interpparser/__init__.py
interpparser/amendments.py
interpparser/gpo_cfr.py
interpparser/layers.py
interpparser/preprocessors.py
interpparser/setup.py
interpparser/tree.py
regparser/__init__.py
regparser/api_writer.py
regparser/citations.py
regparser/content.py
regparser/federalregister.py
regparser/plugins.py
regparser/regs_gov.py
regparser/search.py
regparser/tasks.py
regparser/commands/__init__.py
regparser/commands/annual_editions.py
regparser/commands/annual_version.py
regparser/commands/citations.py
regparser/commands/clear.py
regparser/commands/compare_to.py
regparser/commands/dependency_resolver.py
regparser/commands/diffs.py
regparser/commands/fetch_annual_edition.py
regparser/commands/fetch_sxs.py
regparser/commands/fill_with_rules.py
regparser/commands/full_issuance.py
regparser/commands/full_tests.py
regparser/commands/import_notice.py
regparser/commands/layers.py
regparser/commands/notice_preamble.py
regparser/commands/outline_depths.py
regparser/commands/pipeline.py
regparser/commands/preprocess_notice.py
regparser/commands/proposal_pipeline.py
regparser/commands/proposal_versions.py
regparser/commands/retry.py
regparser/commands/sxs_layers.py
regparser/commands/utils.py
regparser/commands/versions.py
regparser/commands/write_to.py
regparser/diff/__init__.py
regparser/diff/text.py
regparser/diff/tree.py
regparser/grammar/__init__.py
regparser/grammar/amdpar.py
regparser/grammar/appendix.py
regparser/grammar/atomic.py
regparser/grammar/delays.py
regparser/grammar/terms.py
regparser/grammar/tokens.py
regparser/grammar/unified.py
regparser/grammar/utils.py
regparser/history/__init__.py
regparser/history/annual.py
regparser/history/delays.py
regparser/history/versions.py
regparser/index/__init__.py
regparser/index/dependency.py
regparser/index/entry.py
regparser/index/http_cache.py
regparser/layer/__init__.py
regparser/layer/def_finders.py
regparser/layer/external_citations.py
regparser-4.3.1.dist-info/DESCRIPTION.rst
regparser-4.3.1.dist-info/METADATA
regparser-4.3.1.dist-info/RECORD
regparser-4.3.1.dist-info/WHEEL
regparser-4.3.1.dist-info/dependency_links.txt
regparser-4.3.1.dist-info/entry_points.txt
regparser-4.3.1.dist-info/metadata.json
regparser-4.3.1.dist-info/top_level.txt
